{
  "BetOnline.ag": "betonlineag",
  "BetMGM": "betmgm",
  "BetRivers": "betrivers",
  "BetUS": "betus",
  "Bovada": "bovada",
  "DraftKings": "draftkings",
  "FanDuel": "fanduel",
  "LowVig.ag": "lowvig",
  "MyBookie.ag": "mybookieag",
  "PointsBet (US)": "pointsbetus",
  "SuperBook": "superbook",
  "Unibet": "unibet_us",
  "William Hill (Caesars)": "williamhill_us",
  "WynnBET": "wynnbet",
  "betPARX": "betparx",
  "ESPN BET": "espnbet",
  "Fliff": "fliff",
  "Hard Rock Bet": "hardrockbet",
  "SI Sportsbook": "sisportsbook",
  "Tipico": "tipico_us",
  "Wind Creek (Betfred PA)": "windcreek"
}